[{"n": "Electrical Systems Of Maine", "s": "1200 Minot Ave", "c": "Auburn", "st": "ME", "z": "04210", "p": "(207) 241-9355", "r": 4.9, "rv": 548, "lat": 44.0800761, "lng": -70.2810448, "g": "https://www.google.com/maps/dir/?api=1&amp;destination=44.0800761,-70.2810448", "w": "http://www.electricalsystemsofmaine.com"}, {"n": "O'Connor Volkswagen", "s": "188 Riverside Dr", "c": "Augusta", "st": "ME", "z": "04330", "p": "(207) 622-6336", "r": 4.3, "rv": 152, "lat": 44.3290917, "lng": -69.7637275, "g": "https://www.google.com/maps/dir/?api=1&amp;destination=44.3290917,-69.7637275", "w": "https://www.oconnorvw.com"}, {"n": "Wire It Up Electric", "s": "161 Horse Point Rd", "c": "Belgrade", "st": "ME", "z": "04917", "p": "(207) 242-7721", "r": 4.9, "rv": 177, "lat": 44.532367, "lng": -69.80481809999999, "g": "https://www.google.com/maps/dir/?api=1&amp;destination=44.532367,-69.80481809999999", "w": "https://www.wireitupelectricme.com"}, {"n": "Darling's Ford", "s": "403 Hogan Rd", "c": "Bangor", "st": "ME", "z": "04401", "p": "(877) 568-7220", "r": 4.5, "rv": 1064, "lat": 44.8280456, "lng": -68.7395707, "g": "https://www.google.com/maps/dir/?api=1&amp;destination=44.8280456,-68.7395707", "w": "https://www.darlingsford.com"}, {"n": "Neil's Motors Inc", "s": "602 Alfred St", "c": "Biddeford", "st": "ME", "z": "04005", "p": "(207) 282-3156", "r": 4.7, "rv": 253, "lat": 43.4750211, "lng": -70.5204728, "g": "https://www.google.com/maps/dir/?api=1&amp;destination=43.4750211,-70.5204728", "w": "https://neilsmotors.com"}, {"n": "Mainly Electrical", "s": "90 David Dr", "c": "Auburn", "st": "ME", "z": "04210", "p": "(207) 317-9506", "r": 4.8, "rv": 21, "lat": 44.0494359, "lng": -70.2757551, "g": "https://www.google.com/maps/dir/?api=1&amp;destination=44.0494359,-70.2757551", "w": "https://mainly-electrical.com"}, {"n": "Dead River Company", "s": "665 Elm St", "c": "Biddeford", "st": "ME", "z": "04005", "p": "(207) 283-1404", "r": 4.5, "rv": 86, "lat": 43.4604945, "lng": -70.4912101, "g": "https://www.google.com/maps/dir/?api=1&amp;destination=43.4604945,-70.4912101", "w": "https://www.deadriver.com"}, {"n": "Downeast Electrical Services", "s": "432 Elm St Suite F", "c": "Biddeford", "st": "ME", "z": "04005", "p": "(207) 352-3722", "r": 5.0, "rv": 45, "lat": 43.4804248, "lng": -70.4748496, "g": "https://www.google.com/maps/dir/?api=1&amp;destination=43.4804248,-70.4748496", "w": "https://www.downeastelectrical.com"}, {"n": "Ross Tech 360 L.L.C", "s": "201 Mariner Wy #1020", "c": "Biddeford", "st": "ME", "z": "04005", "p": "(207) 247-1051", "r": 4.7, "rv": 19, "lat": 43.4733275, "lng": -70.511211, "g": "https://www.google.com/maps/dir/?api=1&amp;destination=43.4733275,-70.511211", "w": "http://rosstec360.com"}, {"n": "Ox Electric", "s": "100 Alfred St", "c": "Biddeford", "st": "ME", "z": "04005", "p": "(207) 494-4266", "r": 5.0, "rv": 47, "lat": 43.490964, "lng": -70.4564355, "g": "https://www.google.com/maps/dir/?api=1&amp;destination=43.490964,-70.4564355", "w": "https://oxelectricllc.godaddysites.com"}, {"n": "P & M Electrical Contractors", "s": "14 Clark St", "c": "Biddeford", "st": "ME", "z": "04005", "p": "(207) 282-9076", "r": 4.9, "rv": 17, "lat": 43.487453, "lng": -70.4595913, "g": "https://www.google.com/maps/dir/?api=1&amp;destination=43.487453,-70.4595913", "w": "http://pmelectricme.com"}, {"n": "Percy's Electric", "s": "21 St Joseph St", "c": "Biddeford", "st": "ME", "z": "04005", "p": "(207) 282-2342", "r": 0.0, "rv": 0, "lat": 43.49346999999999, "lng": -70.4614856, "g": "https://www.google.com/maps/dir/?api=1&amp;destination=43.49346999999999,-70.4614856", "w": ""}, {"n": "The Pool Man", "s": "75 Western Ave", "c": "Biddeford", "st": "ME", "z": "04005", "p": "(207) 590-9566", "r": 2.3, "rv": 3, "lat": 43.4938112, "lng": -70.46743049999999, "g": "https://www.google.com/maps/dir/?api=1&amp;destination=43.4938112,-70.46743049999999", "w": "http://www.donthepoolman.com"}, {"n": "NorthEast Electrical", "s": "68 Elm St", "c": "Biddeford", "st": "ME", "z": "04005", "p": "(207) 282-3301", "r": 4.4, "rv": 7, "lat": 43.4972127, "lng": -70.4559319, "g": "https://www.google.com/maps/dir/?api=1&amp;destination=43.4972127,-70.4559319", "w": "https://www.needco.com"}, {"n": "BANN Home Electrical Services, LLC", "s": "4 Turner St", "c": "Brunswick", "st": "ME", "z": "04011", "p": "(207) 406-3918", "r": 4.9, "rv": 144, "lat": 43.9111824, "lng": -69.9791438, "g": "https://www.google.com/maps/dir/?api=1&amp;destination=43.9111824,-69.9791438", "w": "https://bannhomeservices.com/electrician-brunswick-me"}, {"n": "Steve's Electric", "s": "379 South St", "c": "Biddeford", "st": "ME", "z": "04005", "p": "(207) 282-6525", "r": 5.0, "rv": 1, "lat": 43.4954196, "lng": -70.4926368, "g": "https://www.google.com/maps/dir/?api=1&amp;destination=43.4954196,-70.4926368", "w": ""}, {"n": "Green Energy Electrical Services LLC", "s": "1700 Long Plains Rd", "c": "Buxton", "st": "ME", "z": "04093", "p": "(207) 812-8634", "r": 5.0, "rv": 6, "lat": 43.6238552, "lng": -70.477648, "g": "https://www.google.com/maps/dir/?api=1&amp;destination=43.6238552,-70.477648", "w": ""}, {"n": "Lambert Electric LLC", "s": "443 Lakeview Dr", "c": "China", "st": "ME", "z": "04358", "p": "(207) 616-9774", "r": 4.9, "rv": 48, "lat": 44.4214856, "lng": -69.5458364, "g": "https://www.google.com/maps/dir/?api=1&amp;destination=44.4214856,-69.5458364", "w": "https://www.lambertelectricme.com"}, {"n": "KVCC Open EV Charger", "s": "Stanley Rd", "c": "Clinton", "st": "ME", "z": "04927", "p": "(207) 453-5079", "r": 0.0, "rv": 0, "lat": 44.6694188, "lng": -69.6310325, "g": "https://www.google.com/maps/dir/?api=1&amp;destination=44.6694188,-69.6310325", "w": "http://kvcc.me.edu"}, {"n": "Moriarty Electric Co", "s": "327 Goodwin Rd", "c": "Eliot", "st": "ME", "z": "03903", "p": "(207) 439-7247", "r": 4.0, "rv": 61, "lat": 43.15276859999999, "lng": -70.76372669999999, "g": "https://www.google.com/maps/dir/?api=1&amp;destination=43.15276859999999,-70.76372669999999", "w": "https://moriartyelectric.com"}, {"n": "Stewart Electrical LLC", "s": "353 Patterson Rd", "c": "Dresden", "st": "ME", "z": "04342", "p": "(800) 281-0023", "r": 4.9, "rv": 40, "lat": 44.0886184, "lng": -69.77493129999999, "g": "https://www.google.com/maps/dir/?api=1&amp;destination=44.0886184,-69.77493129999999", "w": "http://stewartelectricalmaine.com"}, {"n": "ADRENALINE ELECTRIC, LLC", "s": "474 Farmington Falls Rd", "c": "Farmington", "st": "ME", "z": "04938", "p": "(207) 491-5140", "r": 5.0, "rv": 14, "lat": 44.6497597, "lng": -70.11931849999999, "g": "https://www.google.com/maps/dir/?api=1&amp;destination=44.6497597,-70.11931849999999", "w": ""}, {"n": "Maine Solar Solutions", "s": "491 US-1 Suite 20", "c": "Freeport", "st": "ME", "z": "04032", "p": "(207) 871-7191", "r": 4.9, "rv": 192, "lat": 43.8376701, "lng": -70.1235485, "g": "https://www.google.com/maps/dir/?api=1&amp;destination=43.8376701,-70.1235485", "w": "https://mainesolarsolutions.com"}, {"n": "Islesboro Electrical Services Inc", "s": "112 Church Turn Rd", "c": "Islesboro", "st": "ME", "z": "04848", "p": "(207) 734-6974", "r": 1.0, "rv": 1, "lat": 44.3540861, "lng": -68.8964687, "g": "https://www.google.com/maps/dir/?api=1&amp;destination=44.3540861,-68.8964687", "w": ""}, {"n": "East Road Electric, Inc.", "s": "121 E Rd", "c": "Greenville", "st": "ME", "z": "04441", "p": "(207) 695-0304", "r": 5.0, "rv": 6, "lat": 45.4613788, "lng": -69.5563462, "g": "https://www.google.com/maps/dir/?api=1&amp;destination=45.4613788,-69.5563462", "w": "http://eastroadelectric.com"}, {"n": "Affordable Electric", "s": "99 Alden Rd", "c": "Leeds", "st": "ME", "z": "04263", "p": "(207) 754-0103", "r": 5.0, "rv": 3, "lat": 44.26016329999999, "lng": -70.0827456, "g": "https://www.google.com/maps/dir/?api=1&amp;destination=44.26016329999999,-70.0827456", "w": "https://www.affordableelectricme.com"}, {"n": "Thornton Brothers Inc", "s": "125 Main St", "c": "Lincoln", "st": "ME", "z": "04457", "p": "(207) 794-8600", "r": 4.4, "rv": 94, "lat": 45.3679089, "lng": -68.50267509999999, "g": "https://www.google.com/maps/dir/?api=1&amp;destination=45.3679089,-68.50267509999999", "w": "http://thorntonbrothers.net"}, {"n": "Rousseau Electric LLC", "s": "P.O. Box 141,", "c": "North Berwick", "st": "ME", "z": "03906", "p": "(207) 641-9513", "r": 4.8, "rv": 21, "lat": 43.3543427, "lng": -70.7374502, "g": "https://www.google.com/maps/dir/?api=1&amp;destination=43.3543427,-70.7374502", "w": "http://www.rousseauelectricllc.com"}, {"n": "Androscoggin Electric, LLC", "s": "140 Ralph Richardson Rd", "c": "Norway", "st": "ME", "z": "04268", "p": "(207) 739-0335", "r": 5.0, "rv": 4, "lat": 44.2469379, "lng": -70.5652337, "g": "https://www.google.com/maps/dir/?api=1&amp;destination=44.2469379,-70.5652337", "w": ""}, {"n": "Doucette Electric", "s": "2 Arnold Rd", "c": "Old Orchard Beach", "st": "ME", "z": "04064", "p": "(207) 253-9281", "r": 0.0, "rv": 0, "lat": 43.5346516, "lng": -70.4000114, "g": "https://www.google.com/maps/dir/?api=1&amp;destination=43.5346516,-70.4000114", "w": "http://doucette-electric.com"}, {"n": "Chenard Electric LLC", "s": "44 Shadagee Rd", "c": "Saco", "st": "ME", "z": "04072", "p": "(207) 604-2581", "r": 5.0, "rv": 25, "lat": 43.5146672, "lng": -70.45981499999999, "g": "https://www.google.com/maps/dir/?api=1&amp;destination=43.5146672,-70.45981499999999", "w": "http://chenardelectric.com"}, {"n": "Bell Electric", "s": "75 Rainmaker Dr B", "c": "Portland", "st": "ME", "z": "04103", "p": "(857) 350-0950", "r": 5.0, "rv": 53, "lat": 43.694433, "lng": -70.32053719999999, "g": "https://www.google.com/maps/dir/?api=1&amp;destination=43.694433,-70.32053719999999", "w": "https://www.thebellelectric.com"}, {"n": "Sanford Sound", "s": "1438 Main St", "c": "Sanford", "st": "ME", "z": "04073", "p": "(207) 490-4900", "r": 4.8, "rv": 1, "lat": 43.4113423, "lng": -70.74180799999999, "g": "https://www.google.com/maps/dir/?api=1&amp;destination=43.4113423,-70.74180799999999", "w": "http://www.sanfordsound.com"}, {"n": "LaPlante Electric", "s": "717 US-1", "c": "Scarborough", "st": "ME", "z": "04074", "p": "(207) 770-1870", "r": 4.9, "rv": 1285, "lat": 43.56280779999999, "lng": -70.39828469999999, "g": "https://www.google.com/maps/dir/?api=1&amp;destination=43.56280779999999,-70.39828469999999", "w": "https://laplanteelectric.com"}, {"n": "Sundog Solar", "s": "222 E Main St", "c": "Searsport", "st": "ME", "z": "04974", "p": "(207) 548-1100", "r": 4.3, "rv": 67, "lat": 44.4660128, "lng": -68.9023339, "g": "https://www.google.com/maps/dir/?api=1&amp;destination=44.4660128,-68.9023339", "w": "https://sundog.solar/free-estimate-request"}, {"n": "Wilton Electric", "s": "Old Jay St Rd", "c": "Wilton", "st": "ME", "z": "04294", "p": "(207) 645-2484", "r": 0.0, "rv": 0, "lat": 44.5810389, "lng": -70.2356309, "g": "https://www.google.com/maps/dir/?api=1&amp;destination=44.5810389,-70.2356309", "w": "https://www.maine-electrician.com/electrician-in-wilton"}, {"n": "Hight Ford, Inc.", "s": "242 Madison Ave", "c": "Skowhegan", "st": "ME", "z": "04976", "p": "(207) 474-3334", "r": 4.6, "rv": 211, "lat": 44.7780289, "lng": -69.7257857, "g": "https://www.google.com/maps/dir/?api=1&amp;destination=44.7780289,-69.7257857", "w": "https://www.hightford.com"}, {"n": "2 Rivers Electric", "s": "1041 Oyster River Rd", "c": "Warren", "st": "ME", "z": "04864", "p": "(207) 313-1323", "r": 4.9, "rv": 16, "lat": 44.0925909, "lng": -69.21689549999999, "g": "https://www.google.com/maps/dir/?api=1&amp;destination=44.0925909,-69.21689549999999", "w": "https://2riviereselectric.net"}, {"n": "Advanced Generator Solutions", "s": "82 Bangor Rd", "c": "Troy", "st": "ME", "z": "04987", "p": "(207) 949-0050", "r": 4.5, "rv": 4, "lat": 44.6725445, "lng": -69.1993868, "g": "https://www.google.com/maps/dir/?api=1&amp;destination=44.6725445,-69.1993868", "w": "http://agsmaine.com"}, {"n": "Yarmouth Electric", "s": "48 Marina Rd", "c": "Yarmouth", "st": "ME", "z": "04096", "p": "(207) 712-0439", "r": 5.0, "rv": 7, "lat": 43.7972678, "lng": -70.1795115, "g": "https://www.google.com/maps/dir/?api=1&amp;destination=43.7972678,-70.1795115", "w": "https://yarmouthelectric.com"}]